liveeo/perfect_utils/__init__.py
liveeo/perfect_utils/dummy.py
liveeo_databricks-1.0.5.dist-info/LICENSE.txt
liveeo_databricks-1.0.5.dist-info/METADATA
liveeo_databricks-1.0.5.dist-info/WHEEL
liveeo_databricks-1.0.5.dist-info/RECORD
